Metadata-Version: 2.4
Name: nonebot-plugin-werewolf
Version: 1.1.13
Summary: 适用于 Nonebot2 的狼人杀插件
Author-email: wyf7685 <wyf7685@163.com>
License: MIT
Project-URL: homepage, https://github.com/wyf7685/nonebot-plugin-werewolf
Project-URL: repository, https://github.com/wyf7685/nonebot-plugin-werewolf
Project-URL: bug-tracker, https://github.com/wyf7685/nonebot-plugin-werewolf/issues
Requires-Python: >=3.10
License-File: LICENSE
Requires-Dist: nonebot2>=2.4.0
Requires-Dist: nonebot-plugin-alconna>=0.58.0
Requires-Dist: nonebot-plugin-localstore>=0.7.1
Requires-Dist: nonebot-plugin-uninfo>=0.8.0
Requires-Dist: nonebot-plugin-waiter>=0.8.0
Requires-Dist: anyio>=4.6.0
Dynamic: license-file
